symdexer/__init__.py
symdexer/__main__.py
symdexer/__version__.py
symdexer/cache.py
symdexer/modules.py
symdexer/parser.py
symdexer/symbols.py
symdexer-0.2.10.dist-info/LICENSE.txt
symdexer-0.2.10.dist-info/METADATA
symdexer-0.2.10.dist-info/WHEEL
symdexer-0.2.10.dist-info/entry_points.txt
symdexer-0.2.10.dist-info/top_level.txt
symdexer-0.2.10.dist-info/RECORD
