Metadata-Version: 2.1
Name: symdexer
Version: 0.2.10
Summary: A CLI for finding and indexing symbols
Author-email: AntiMach <themachinumps@gmail.com>
Project-URL: Homepage, https://github.com/antimach/symdexer
Classifier: Programming Language :: Python :: 3
Classifier: License :: OSI Approved :: MIT License
Classifier: Operating System :: OS Independent
Requires-Python: >=3.7
License-File: LICENSE.txt
